aut_project/__init__.py
aut_project/controllers.py
aut_project/dc_motor.py
aut_project/parameters.py
aut_project/scope.py
aut_project/signals.py
aut_project/simulation.py
simulations/__init__.py
simulations/simu_cascade.py
simulations/simu_no_limits.py
simulations/simu_pid.py
simulations/simu_sine_ref.py
simulations/simu_square_ref.py
simulations/simu_triangle_ref.py
aut_project-1.0.dist-info/METADATA
aut_project-1.0.dist-info/WHEEL
aut_project-1.0.dist-info/top_level.txt
aut_project-1.0.dist-info/RECORD
