Metadata-Version: 2.4
Name: aut_project
Version: 1.0
Summary: DC motor simulation and control package
Author: Zsombor Ménes
Requires-Dist: numpy
Requires-Dist: matplotlib
Dynamic: author
Dynamic: requires-dist
Dynamic: summary
